odoo/addons/slow_statement_logger/README.rst
odoo/addons/slow_statement_logger/__init__.py
odoo/addons/slow_statement_logger/__manifest__.py
odoo/addons/slow_statement_logger/i18n/slow_statement_logger.pot
odoo/addons/slow_statement_logger/readme/CONTRIBUTORS.rst
odoo/addons/slow_statement_logger/readme/DESCRIPTION.rst
odoo/addons/slow_statement_logger/readme/USAGE.rst
odoo/addons/slow_statement_logger/static/description/icon.png
odoo/addons/slow_statement_logger/static/description/index.html
odoo14_addon_slow_statement_logger-14.0.1.0.1.dist-info/METADATA
odoo14_addon_slow_statement_logger-14.0.1.0.1.dist-info/WHEEL
odoo14_addon_slow_statement_logger-14.0.1.0.1.dist-info/top_level.txt
odoo14_addon_slow_statement_logger-14.0.1.0.1.dist-info/RECORD
